{"202012011838261606858706":{"fecha":"01-12-2020 18:38:26","id_producto":"2","nombre":"prueba 2","apellido":"p2","comentario":"p2","estrellas":"2","email":"prueba@gmail.com"},"202012011840421606858842":{"fecha":"01-12-2020 18:40:42","id_producto":"2","nombre":"p3","apellido":"p3","comentario":"p3","estrellas":"3","email":"prueba@gmail.com"},"202012011840531606858853":{"fecha":"01-12-2020 18:40:53","id_producto":"2","nombre":"p4","apellido":"4","comentario":"p4","estrellas":"4","email":"prueba@gmail.com"},"202012011841021606858862":{"fecha":"01-12-2020 18:41:02","id_producto":"2","nombre":"p5","apellido":"p5","comentario":"p5","estrellas":"5","email":"prueba@gmail.com"},"202012012237331606873053":{"fecha":"01-12-2020 22:37:33","id_producto":"2","nombre":"Eluney Jeronimo","apellido":"iza","comentario":"Buenisimo","estrellas":"4","email":"eluneyiza99@gmail.com"}}